livekit/plugins/simplismart/__init__.py
livekit/plugins/simplismart/log.py
livekit/plugins/simplismart/models.py
livekit/plugins/simplismart/py.typed
livekit/plugins/simplismart/stt.py
livekit/plugins/simplismart/tts.py
livekit/plugins/simplismart/version.py
livekit_plugins_simplismart-1.3.12rc1.dist-info/METADATA
livekit_plugins_simplismart-1.3.12rc1.dist-info/WHEEL
livekit_plugins_simplismart-1.3.12rc1.dist-info/RECORD
